{"nm":"Comp 1","ddd":0,"h":600,"w":750,"meta":{"g":"@lottiefiles/toolkit-js 0.25.4"},"layers":[{"ty":0,"nm":"2","sr":1,"st":0,"op":120,"ip":0,"hd":false,"ddd":0,"bm":0,"hasMask":false,"ao":0,"ks":{"a":{"a":0,"k":[500,500,0],"ix":1},"s":{"a":0,"k":[100,100,100],"ix":6},"sk":{"a":0,"k":0},"p":{"a":0,"k":[375,300,0],"ix":2},"r":{"a":0,"k":0,"ix":10},"sa":{"a":0,"k":0},"o":{"a":0,"k":100,"ix":11}},"ef":[],"w":1000,"h":1000,"refId":"comp_0","ind":1}],"v":"5.7.4","fr":30,"op":120,"ip":0,"assets":[{"nm":"","id":"comp_0","layers":[{"ty":4,"nm":"Shape Layer 1","sr":1,"st":0,"op":120,"ip":0,"hd":false,"ddd":0,"bm":0,"hasMask":false,"ao":0,"ks":{"a":{"a":0,"k":[1.5,-141,0],"ix":1},"s":{"a":0,"k":[54,54,100],"ix":6},"sk":{"a":0,"k":0},"p":{"a":0,"k":[501.5,353,0],"ix":2},"r":{"a":0,"k":0,"ix":10},"sa":{"a":0,"k":0},"o":{"a":0,"k":100,"ix":11}},"ef":[{"ty":0,"mn":"ADBE Fill","nm":"Fill","ix":1,"en":1,"ef":[{"ty":10,"mn":"ADBE Fill-0001","nm":"Fill Mask","ix":1,"v":{"a":0,"k":0,"ix":1}},{"ty":7,"mn":"ADBE Fill-0007","nm":"All Masks","ix":2,"v":{"a":0,"k":0,"ix":2}},{"ty":2,"mn":"ADBE Fill-0002","nm":"Color","ix":3,"v":{"a":0,"k":[0.3804,0.1843,0.0549],"ix":3}},{"ty":7,"mn":"ADBE Fill-0006","nm":"Invert","ix":4,"v":{"a":0,"k":0,"ix":4}},{"ty":0,"mn":"ADBE Fill-0003","nm":"Horizontal Feather","ix":5,"v":{"a":0,"k":0,"ix":5}},{"ty":0,"mn":"ADBE Fill-0004","nm":"Vertical Feather","ix":6,"v":{"a":0,"k":0,"ix":6}},{"ty":0,"mn":"ADBE Fill-0005","nm":"Opacity","ix":7,"v":{"a":0,"k":1,"ix":7}}]}],"shapes":[{"ty":"gr","bm":0,"hd":false,"mn":"ADBE Vector Group","nm":"Ellipse 1","ix":1,"cix":2,"np":3,"it":[{"ty":"el","bm":0,"hd":false,"mn":"ADBE Vector Shape - Ellipse","nm":"Ellipse Path 1","d":1,"p":{"a":0,"k":[0,0],"ix":3},"s":{"a":0,"k":[34,34],"ix":2}},{"ty":"st","bm":0,"hd":false,"mn":"ADBE Vector Graphic - Stroke","nm":"Stroke 1","lc":1,"lj":1,"ml":4,"o":{"a":0,"k":100,"ix":4},"w":{"a":0,"k":0,"ix":5},"c":{"a":0,"k":[1,1,1],"ix":3}},{"ty":"fl","bm":0,"hd":false,"mn":"ADBE Vector Graphic - Fill","nm":"Fill 1","c":{"a":0,"k":[0.2118,0.7961,0.9922],"ix":4},"r":1,"o":{"a":0,"k":100,"ix":5}},{"ty":"tr","a":{"a":0,"k":[0,0],"ix":1},"s":{"a":0,"k":[100,100],"ix":3},"sk":{"a":0,"k":0,"ix":4},"p":{"a":0,"k":[1,-141],"ix":2},"r":{"a":0,"k":0,"ix":6},"sa":{"a":0,"k":0,"ix":5},"o":{"a":0,"k":100,"ix":7}}]}],"ind":1},{"ty":0,"nm":"Left","sr":1,"st":0,"op":120,"ip":0,"hd":false,"ddd":0,"bm":0,"hasMask":false,"ao":0,"ks":{"a":{"a":0,"k":[500,500,0],"ix":1},"s":{"a":0,"k":[100,100,100],"ix":6},"sk":{"a":0,"k":0},"p":{"a":0,"k":[256,256,0],"ix":2},"r":{"a":0,"k":0,"ix":10},"sa":{"a":0,"k":0},"o":{"a":0,"k":100,"ix":11}},"ef":[],"w":1000,"h":1000,"refId":"comp_1","ind":2,"parent":4},{"ty":0,"nm":"Right","sr":1,"st":0,"op":120,"ip":0,"hd":false,"ddd":0,"bm":0,"hasMask":false,"ao":0,"ks":{"a":{"a":0,"k":[500,500,0],"ix":1},"s":{"a":0,"k":[100,100,100],"ix":6},"sk":{"a":0,"k":0},"p":{"a":0,"k":[256,256,0],"ix":2},"r":{"a":0,"k":0,"ix":10},"sa":{"a":0,"k":0},"o":{"a":0,"k":100,"ix":11}},"ef":[],"w":1000,"h":1000,"refId":"comp_3","ind":3,"parent":4},{"ty":4,"nm":"Handle","sr":1,"st":0,"op":120,"ip":0,"hd":false,"ddd":0,"bm":0,"hasMask":false,"ao":0,"ks":{"a":{"a":0,"k":[254.997,107.997,0],"ix":1},"s":{"a":0,"k":[100,100,100],"ix":6},"sk":{"a":0,"k":0},"p":{"a":0,"k":[498.997,351.997,0],"ix":2},"r":{"a":1,"k":[{"o":{"x":0.56,"y":0},"i":{"x":0.499,"y":1},"s":[20],"t":0},{"o":{"x":0.529,"y":0},"i":{"x":0.667,"y":1},"s":[-15],"t":30},{"o":{"x":0.333,"y":0},"i":{"x":0.415,"y":1},"s":[27],"t":60},{"o":{"x":0.569,"y":0},"i":{"x":0.667,"y":1},"s":[-15],"t":90},{"s":[20],"t":119}],"ix":10},"sa":{"a":0,"k":0},"o":{"a":0,"k":100,"ix":11}},"ef":[{"ty":0,"mn":"ADBE FreePin3","nm":"Puppet","ix":1,"en":1,"ef":[{"ty":7,"mn":"ADBE FreePin3 Puppet Engine","nm":"Puppet Engine","ix":1,"v":{"a":0,"k":2,"ix":1}},{"ty":0,"mn":"ADBE FreePin3 Auto Rotate Pins","nm":"Mesh Rotation Refinement","ix":2,"v":{"a":0,"k":20,"ix":2}},{"ty":7,"mn":"ADBE FreePin3 On Transparent","nm":"On Transparent","ix":3,"v":{"a":0,"k":0,"ix":3}}]}],"shapes":[{"ty":"gr","bm":0,"hd":false,"mn":"ADBE Vector Group","nm":"Group 1","ix":1,"cix":2,"np":2,"it":[{"ty":"sh","bm":0,"hd":false,"mn":"ADBE Vector Shape - Group","nm":"Path 1","ix":1,"d":1,"ks":{"a":0,"k":{"c":true,"i":[[1.358,0.008],[1.42,0.952],[18.622,-0.009],[0,0],[15.499,-10.358],[2.777,1.367],[0,0],[0,0],[0,0],[-20.302,-0.009],[0,0],[-17.393,-10.505],[0,0],[0,0],[0,0]],"o":[[-1.713,0],[-15.481,-10.35],[0,0],[-18.64,-0.017],[-2.587,1.705],[0,0],[0,0],[0,0],[17.376,-10.497],[0,0],[20.327,-0.017],[0,0],[0,0],[0,0],[-1.211,0.606]],"v":[[155.732,17.087],[150.929,15.633],[98.619,-0.22],[-98.637,-0.22],[-150.991,15.633],[-159.644,16.178],[-194.258,-1.129],[-186.522,-16.619],[-156.235,-1.493],[-98.637,-17.528],[98.619,-17.528],[156.277,-1.493],[186.521,-16.619],[194.257,-1.129],[159.643,16.178]]},"ix":2}},{"ty":"fl","bm":0,"hd":false,"mn":"ADBE Vector Graphic - Fill","nm":"Fill 1","c":{"a":0,"k":[0.5686,0.3373,0.1843],"ix":4},"r":1,"o":{"a":0,"k":100,"ix":5}},{"ty":"tr","a":{"a":0,"k":[0,0],"ix":1},"s":{"a":0,"k":[100,100],"ix":3},"sk":{"a":0,"k":0,"ix":4},"p":{"a":0,"k":[256.028,117.762],"ix":2},"r":{"a":0,"k":0,"ix":6},"sa":{"a":0,"k":0,"ix":5},"o":{"a":0,"k":100,"ix":7}}]}],"ind":4},{"ty":4,"nm":"Stand","sr":1,"st":0,"op":120,"ip":0,"hd":false,"ddd":0,"bm":0,"hasMask":false,"ao":0,"ks":{"a":{"a":0,"k":[255.997,255.997,0],"ix":1},"s":{"a":0,"k":[100,100,100],"ix":6},"sk":{"a":0,"k":0},"p":{"a":0,"k":[499.997,499.997,0],"ix":2},"r":{"a":0,"k":0,"ix":10},"sa":{"a":0,"k":0},"o":{"a":0,"k":100,"ix":11}},"ef":[],"shapes":[{"ty":"gr","bm":0,"hd":false,"mn":"ADBE Vector Group","nm":"Group 1","ix":1,"cix":2,"np":2,"it":[{"ty":"sh","bm":0,"hd":false,"mn":"ADBE Vector Shape - Group","nm":"Path 1","ix":1,"d":1,"ks":{"a":0,"k":{"c":true,"i":[[0,0],[0,0],[0,0],[0,0]],"o":[[0,0],[0,0],[0,0],[0,0]],"v":[[-43.268,-8.654],[43.268,-8.654],[43.268,8.654],[-43.268,8.654]]},"ix":2}},{"ty":"fl","bm":0,"hd":false,"mn":"ADBE Vector Graphic - Fill","nm":"Fill 1","c":{"a":0,"k":[0.9765,0.7059,0.302],"ix":4},"r":1,"o":{"a":0,"k":100,"ix":5}},{"ty":"tr","a":{"a":0,"k":[0,0],"ix":1},"s":{"a":0,"k":[100,100],"ix":3},"sk":{"a":0,"k":0,"ix":4},"p":{"a":0,"k":[255.997,74.275],"ix":2},"r":{"a":0,"k":0,"ix":6},"sa":{"a":0,"k":0,"ix":5},"o":{"a":0,"k":100,"ix":7}}]},{"ty":"gr","bm":0,"hd":false,"mn":"ADBE Vector Group","nm":"Group 2","ix":2,"cix":2,"np":2,"it":[{"ty":"sh","bm":0,"hd":false,"mn":"ADBE Vector Shape - Group","nm":"Path 1","ix":1,"d":1,"ks":{"a":0,"k":{"c":true,"i":[[2.216,0],[2.622,-0.874],[3.436,-13.829],[0,0],[0,0],[0,0],[14.486,3.625]],"o":[[-2.76,0.043],[13.603,4.258],[0,0],[0,0],[0,0],[3.626,-14.477],[-2.137,-0.529]],"v":[[-10.864,-34.615],[-18.981,-33.229],[-0.879,-1.029],[-9.783,34.615],[6.443,34.615],[15.355,-1.029],[-4.306,-33.808]]},"ix":2}},{"ty":"fl","bm":0,"hd":false,"mn":"ADBE Vector Graphic - Fill","nm":"Fill 1","c":{"a":0,"k":[0.9804,0.5961,0.1843],"ix":4},"r":1,"o":{"a":0,"k":100,"ix":5}},{"ty":"tr","a":{"a":0,"k":[0,0],"ix":1},"s":{"a":0,"k":[100,100],"ix":3},"sk":{"a":0,"k":0,"ix":4},"p":{"a":0,"k":[266.861,39.661],"ix":2},"r":{"a":0,"k":0,"ix":6},"sa":{"a":0,"k":0,"ix":5},"o":{"a":0,"k":100,"ix":7}}]},{"ty":"gr","bm":0,"hd":false,"mn":"ADBE Vector Group","nm":"Group 3","ix":3,"cix":2,"np":2,"it":[{"ty":"sh","bm":0,"hd":false,"mn":"ADBE Vector Shape - Group","nm":"Path 1","ix":1,"d":1,"ks":{"a":0,"k":{"c":true,"i":[[0,0],[0,0],[0,0],[-14.486,3.625],[-2.206,0],[0,-14.927],[0.537,-2.146]],"o":[[0,0],[0,0],[-3.626,-14.477],[2.146,-0.537],[14.927,0],[0,2.215],[0,0]],"v":[[18.717,34.614],[-15.896,34.614],[-24.81,-1.03],[-5.149,-33.809],[1.41,-34.614],[28.435,-7.589],[27.63,-1.03]]},"ix":2}},{"ty":"fl","bm":0,"hd":false,"mn":"ADBE Vector Graphic - Fill","nm":"Fill 1","c":{"a":0,"k":[0.9765,0.7059,0.302],"ix":4},"r":1,"o":{"a":0,"k":100,"ix":5}},{"ty":"tr","a":{"a":0,"k":[0,0],"ix":1},"s":{"a":0,"k":[100,100],"ix":3},"sk":{"a":0,"k":0,"ix":4},"p":{"a":0,"k":[254.586,39.66],"ix":2},"r":{"a":0,"k":0,"ix":6},"sa":{"a":0,"k":0,"ix":5},"o":{"a":0,"k":100,"ix":7}}]},{"ty":"gr","bm":0,"hd":false,"mn":"ADBE Vector Group","nm":"Group 4","ix":4,"cix":2,"np":2,"it":[{"ty":"sh","bm":0,"hd":false,"mn":"ADBE Vector Shape - Group","nm":"Path 1","ix":1,"d":1,"ks":{"a":0,"k":{"c":true,"i":[[0,0],[0,0],[0,0],[0,0]],"o":[[0,0],[0,0],[0,0],[0,0]],"v":[[-17.307,-181.723],[17.307,-181.723],[17.307,181.723],[-17.307,181.723]]},"ix":2}},{"ty":"fl","bm":0,"hd":false,"mn":"ADBE Vector Graphic - Fill","nm":"Fill 1","c":{"a":0,"k":[0.5686,0.3373,0.1843],"ix":4},"r":1,"o":{"a":0,"k":100,"ix":5}},{"ty":"tr","a":{"a":0,"k":[0,0],"ix":1},"s":{"a":0,"k":[100,100],"ix":3},"sk":{"a":0,"k":0,"ix":4},"p":{"a":0,"k":[255.997,255.997],"ix":2},"r":{"a":0,"k":0,"ix":6},"sa":{"a":0,"k":0,"ix":5},"o":{"a":0,"k":100,"ix":7}}]},{"ty":"gr","bm":0,"hd":false,"mn":"ADBE Vector Group","nm":"Group 5","ix":5,"cix":2,"np":2,"it":[{"ty":"sh","bm":0,"hd":false,"mn":"ADBE Vector Shape - Group","nm":"Path 1","ix":1,"d":1,"ks":{"a":0,"k":{"c":true,"i":[[0,0],[0,0],[0,0],[0,0]],"o":[[0,0],[0,0],[0,0],[0,0]],"v":[[51.921,17.307],[-51.921,17.307],[-17.307,-17.307],[17.307,-17.307]]},"ix":2}},{"ty":"fl","bm":0,"hd":false,"mn":"ADBE Vector Graphic - Fill","nm":"Fill 1","c":{"a":0,"k":[0.9765,0.7059,0.302],"ix":4},"r":1,"o":{"a":0,"k":100,"ix":5}},{"ty":"tr","a":{"a":0,"k":[0,0],"ix":1},"s":{"a":0,"k":[100,100],"ix":3},"sk":{"a":0,"k":0,"ix":4},"p":{"a":0,"k":[255.997,455.027],"ix":2},"r":{"a":0,"k":0,"ix":6},"sa":{"a":0,"k":0,"ix":5},"o":{"a":0,"k":100,"ix":7}}]},{"ty":"gr","bm":0,"hd":false,"mn":"ADBE Vector Group","nm":"Group 6","ix":6,"cix":2,"np":2,"it":[{"ty":"sh","bm":0,"hd":false,"mn":"ADBE Vector Shape - Group","nm":"Path 1","ix":1,"d":1,"ks":{"a":0,"k":{"c":true,"i":[[19.116,0],[0,0],[0,-19.116],[0,0]],"o":[[0,0],[19.116,0],[0,0],[0,-19.116]],"v":[[17.307,-17.307],[-51.921,-17.307],[-17.307,17.307],[51.921,17.307]]},"ix":2}},{"ty":"fl","bm":0,"hd":false,"mn":"ADBE Vector Graphic - Fill","nm":"Fill 1","c":{"a":0,"k":[0.9804,0.5961,0.1843],"ix":4},"r":1,"o":{"a":0,"k":100,"ix":5}},{"ty":"tr","a":{"a":0,"k":[0,0],"ix":1},"s":{"a":0,"k":[100,100],"ix":3},"sk":{"a":0,"k":0,"ix":4},"p":{"a":0,"k":[325.225,489.641],"ix":2},"r":{"a":0,"k":0,"ix":6},"sa":{"a":0,"k":0,"ix":5},"o":{"a":0,"k":100,"ix":7}}]},{"ty":"gr","bm":0,"hd":false,"mn":"ADBE Vector Group","nm":"Group 7","ix":7,"cix":2,"np":2,"it":[{"ty":"sh","bm":0,"hd":false,"mn":"ADBE Vector Shape - Group","nm":"Path 1","ix":1,"d":1,"ks":{"a":0,"k":{"c":true,"i":[[0,-19.116],[0,0],[-19.116,0],[0,0]],"o":[[0,0],[0,-19.116],[0,0],[19.116,0]],"v":[[121.148,17.307],[-121.148,17.307],[-86.535,-17.307],[86.534,-17.307]]},"ix":2}},{"ty":"fl","bm":0,"hd":false,"mn":"ADBE Vector Graphic - Fill","nm":"Fill 1","c":{"a":0,"k":[0.9765,0.7059,0.302],"ix":4},"r":1,"o":{"a":0,"k":100,"ix":5}},{"ty":"tr","a":{"a":0,"k":[0,0],"ix":1},"s":{"a":0,"k":[100,100],"ix":3},"sk":{"a":0,"k":0,"ix":4},"p":{"a":0,"k":[255.997,489.641],"ix":2},"r":{"a":0,"k":0,"ix":6},"sa":{"a":0,"k":0,"ix":5},"o":{"a":0,"k":100,"ix":7}}]}],"ind":5}]},{"nm":"","id":"comp_1","layers":[{"ty":0,"nm":"Left Ind","sr":1,"st":0,"op":120,"ip":0,"hd":false,"ddd":0,"bm":0,"hasMask":false,"ao":0,"ks":{"a":{"a":0,"k":[342,358,0],"ix":1},"s":{"a":0,"k":[100,100,100],"ix":6},"sk":{"a":0,"k":0},"p":{"a":0,"k":[342,358,0],"ix":2},"r":{"a":1,"k":[{"o":{"x":0.333,"y":0},"i":{"x":0.667,"y":1},"s":[0],"t":0},{"o":{"x":0.333,"y":0},"i":{"x":0.667,"y":1},"s":[-18],"t":31},{"o":{"x":0.333,"y":0},"i":{"x":0.833,"y":1},"s":[24],"t":57},{"o":{"x":0.167,"y":0},"i":{"x":0.667,"y":1},"s":[0],"t":80},{"o":{"x":0.333,"y":0},"i":{"x":0.833,"y":1},"s":[-10],"t":100},{"s":[0],"t":119}],"ix":10},"sa":{"a":0,"k":0},"o":{"a":0,"k":100,"ix":11}},"ef":[],"w":1000,"h":1000,"refId":"comp_2","ind":1}]},{"nm":"","id":"comp_2","layers":[{"ty":4,"nm":"Left","sr":1,"st":0,"op":120,"ip":0,"hd":false,"ddd":0,"bm":0,"hasMask":false,"ao":0,"ks":{"a":{"a":0,"k":[100.997,116.997,0],"ix":1},"s":{"a":0,"k":[100,100,100],"ix":6},"sk":{"a":0,"k":0},"p":{"a":0,"k":[344.997,360.997,0],"ix":2},"r":{"a":0,"k":0,"ix":10},"sa":{"a":0,"k":0},"o":{"a":0,"k":100,"ix":11}},"ef":[],"shapes":[{"ty":"gr","bm":0,"hd":false,"mn":"ADBE Vector Group","nm":"Group 1","ix":1,"cix":2,"np":2,"it":[{"ty":"sh","bm":0,"hd":false,"mn":"ADBE Vector Shape - Group","nm":"Path 1","ix":1,"d":1,"ks":{"a":0,"k":{"c":true,"i":[[0,0],[28.678,0],[0,0],[0,28.678]],"o":[[0,28.678],[0,0],[28.678,0],[0,0]],"v":[[0,-25.96],[-51.921,25.961],[0,25.961],[51.921,-25.96]]},"ix":2}},{"ty":"fl","bm":0,"hd":false,"mn":"ADBE Vector Graphic - Fill","nm":"Fill 1","c":{"a":0,"k":[0.9804,0.5961,0.1843],"ix":4},"r":1,"o":{"a":0,"k":100,"ix":5}},{"ty":"tr","a":{"a":0,"k":[0,0],"ix":1},"s":{"a":0,"k":[100,100],"ix":3},"sk":{"a":0,"k":0,"ix":4},"p":{"a":0,"k":[143.502,342.532],"ix":2},"r":{"a":0,"k":0,"ix":6},"sa":{"a":0,"k":0,"ix":5},"o":{"a":0,"k":100,"ix":7}}]},{"ty":"gr","bm":0,"hd":false,"mn":"ADBE Vector Group","nm":"Group 2","ix":2,"cix":2,"np":2,"it":[{"ty":"sh","bm":0,"hd":false,"mn":"ADBE Vector Shape - Group","nm":"Path 1","ix":1,"d":1,"ks":{"a":0,"k":{"c":true,"i":[[0,28.677],[0,0],[28.678,0],[0,0]],"o":[[0,0],[0,28.678],[0,0],[-28.668,-0.001]],"v":[[-95.188,-25.96],[95.188,-25.96],[43.267,25.961],[-43.268,25.961]]},"ix":2}},{"ty":"fl","bm":0,"hd":false,"mn":"ADBE Vector Graphic - Fill","nm":"Fill 1","c":{"a":0,"k":[0.9765,0.7059,0.302],"ix":4},"r":1,"o":{"a":0,"k":100,"ix":5}},{"ty":"tr","a":{"a":0,"k":[0,0],"ix":1},"s":{"a":0,"k":[100,100],"ix":3},"sk":{"a":0,"k":0,"ix":4},"p":{"a":0,"k":[100.235,342.532],"ix":2},"r":{"a":0,"k":0,"ix":6},"sa":{"a":0,"k":0,"ix":5},"o":{"a":0,"k":100,"ix":7}}]},{"ty":"gr","bm":0,"hd":false,"mn":"ADBE Vector Group","nm":"Group 3","ix":3,"cix":2,"np":4,"it":[{"ty":"sh","bm":0,"hd":false,"mn":"ADBE Vector Shape - Group","nm":"Path 1","ix":1,"d":1,"ks":{"a":0,"k":{"c":true,"i":[[1.998,4.344],[0,0],[0,0],[4.345,1.99],[-1.99,4.344],[0,0],[-4.345,-1.991],[-0.866,-1.886],[0,0],[4.345,-1.99]],"o":[[0,0],[0,0],[-1.99,4.344],[-4.344,-1.99],[0,0],[1.99,-4.344],[1.886,0.865],[0,0],[1.99,4.344],[-4.344,1.999]],"v":[[83.114,103.512],[-0.6,-79.145],[-84.314,103.512],[-95.79,107.77],[-100.048,96.296],[-8.467,-103.521],[3.008,-107.778],[7.266,-103.521],[98.846,96.296],[94.588,107.77]]},"ix":2}},{"ty":"fl","bm":0,"hd":false,"mn":"ADBE Vector Graphic - Fill","nm":"Fill 1","c":{"a":0,"k":[0.9412,0.8941,0.8392],"ix":4},"r":1,"o":{"a":0,"k":100,"ix":5}},{"ty":"tr","a":{"a":0,"k":[0,0],"ix":1},"s":{"a":0,"k":[100,100],"ix":3},"sk":{"a":0,"k":0,"ix":4},"p":{"a":0,"k":[100.836,208.802],"ix":2},"r":{"a":0,"k":0,"ix":6},"sa":{"a":0,"k":0,"ix":5},"o":{"a":0,"k":100,"ix":7}}]}],"ind":1}]},{"nm":"","id":"comp_3","layers":[{"ty":0,"nm":"Right Comp 1","sr":1,"st":0,"op":120,"ip":0,"hd":false,"ddd":0,"bm":0,"hasMask":false,"ao":0,"ks":{"a":{"a":0,"k":[656,354,0],"ix":1},"s":{"a":0,"k":[100,100,100],"ix":6},"sk":{"a":0,"k":0},"p":{"a":0,"k":[656,354,0],"ix":2},"r":{"a":1,"k":[{"o":{"x":0.053,"y":0.005},"i":{"x":0,"y":0.908},"s":[-15],"t":0},{"o":{"x":0.167,"y":0},"i":{"x":0.667,"y":1},"s":[-25],"t":28},{"o":{"x":0.333,"y":0},"i":{"x":0.667,"y":1},"s":[25],"t":50},{"o":{"x":0.333,"y":0},"i":{"x":0.667,"y":1},"s":[-30],"t":70},{"o":{"x":0.333,"y":0},"i":{"x":0.667,"y":1},"s":[-30],"t":91},{"o":{"x":0.333,"y":0},"i":{"x":0.667,"y":1},"s":[10],"t":108},{"s":[-12],"t":119}],"ix":10},"sa":{"a":0,"k":0},"o":{"a":0,"k":100,"ix":11}},"ef":[],"w":1000,"h":1000,"refId":"comp_4","ind":1}]},{"nm":"","id":"comp_4","layers":[{"ty":0,"nm":"gears","sr":1,"st":0,"op":120,"ip":0,"hd":false,"ddd":0,"bm":0,"hasMask":false,"ao":0,"ks":{"a":{"a":0,"k":[257.5,257.5,0],"ix":1},"s":{"a":0,"k":[14,14,100],"ix":6},"sk":{"a":0,"k":0},"p":{"a":1,"k":[{"o":{"x":0.333,"y":0},"i":{"x":0.667,"y":1},"s":[617,525,0],"t":0,"ti":[0,0,0],"to":[13,0,0]},{"o":{"x":0.333,"y":0},"i":{"x":0.667,"y":1},"s":[695,525,0],"t":36.14,"ti":[0,0,0],"to":[0,0,0]},{"o":{"x":0.333,"y":0},"i":{"x":1,"y":1},"s":[617,525,0],"t":58,"ti":[-21.497,0,0],"to":[0,0,0]},{"o":{"x":0,"y":0},"i":{"x":0.667,"y":1},"s":[661.817,495,0],"t":66,"ti":[-5.213,0,0],"to":[14.393,0,0]},{"o":{"x":0.167,"y":0},"i":{"x":0.667,"y":1},"s":[695,525,0],"t":73,"ti":[0,0,0],"to":[13,0,0]},{"o":{"x":0.283,"y":0},"i":{"x":0.706,"y":1},"s":[617,525,0],"t":90,"ti":[0,0,0],"to":[0,0,0]},{"o":{"x":0.333,"y":0},"i":{"x":0.573,"y":1},"s":[695,525,0],"t":103,"ti":[13,0,0],"to":[0,0,0]},{"s":[617,525,0],"t":119}],"ix":2},"r":{"a":1,"k":[{"o":{"x":0.333,"y":0},"i":{"x":0.667,"y":1},"s":[0],"t":0},{"o":{"x":0.333,"y":0},"i":{"x":0.667,"y":1},"s":[90],"t":36.14},{"o":{"x":0.333,"y":0},"i":{"x":0.667,"y":1},"s":[0],"t":50},{"o":{"x":0.167,"y":0},"i":{"x":0.667,"y":1},"s":[90],"t":73},{"o":{"x":0.333,"y":0},"i":{"x":0.667,"y":1},"s":[0],"t":90},{"o":{"x":0.333,"y":0},"i":{"x":0.667,"y":1},"s":[90],"t":103},{"s":[0],"t":119}],"ix":10},"sa":{"a":0,"k":0},"o":{"a":0,"k":100,"ix":11}},"ef":[],"w":515,"h":515,"refId":"comp_5","ind":1},{"ty":4,"nm":"Right","sr":1,"st":0,"op":120,"ip":0,"hd":false,"ddd":0,"bm":0,"hasMask":false,"ao":0,"ks":{"a":{"a":0,"k":[410.997,121.997,0],"ix":1},"s":{"a":0,"k":[100,100,100],"ix":6},"sk":{"a":0,"k":0},"p":{"a":0,"k":[654.997,365.997,0],"ix":2},"r":{"a":0,"k":0,"ix":10},"sa":{"a":0,"k":0},"o":{"a":0,"k":100,"ix":11}},"ef":[],"shapes":[{"ty":"gr","bm":0,"hd":false,"mn":"ADBE Vector Group","nm":"Group 1","ix":1,"cix":2,"np":2,"it":[{"ty":"sh","bm":0,"hd":false,"mn":"ADBE Vector Shape - Group","nm":"Path 1","ix":1,"d":1,"ks":{"a":0,"k":{"c":true,"i":[[0,0],[28.678,0],[0,0],[0,28.678]],"o":[[0,28.678],[0,0],[28.678,0],[0,0]],"v":[[0,-25.96],[-51.921,25.961],[0,25.961],[51.921,-25.96]]},"ix":2}},{"ty":"fl","bm":0,"hd":false,"mn":"ADBE Vector Graphic - Fill","nm":"Fill 1","c":{"a":0,"k":[0.9804,0.5961,0.1843],"ix":4},"r":1,"o":{"a":0,"k":100,"ix":5}},{"ty":"tr","a":{"a":0,"k":[0,0],"ix":1},"s":{"a":0,"k":[100,100],"ix":3},"sk":{"a":0,"k":0,"ix":4},"p":{"a":0,"k":[455.027,342.532],"ix":2},"r":{"a":0,"k":0,"ix":6},"sa":{"a":0,"k":0,"ix":5},"o":{"a":0,"k":100,"ix":7}}]},{"ty":"gr","bm":0,"hd":false,"mn":"ADBE Vector Group","nm":"Group 2","ix":2,"cix":2,"np":2,"it":[{"ty":"sh","bm":0,"hd":false,"mn":"ADBE Vector Shape - Group","nm":"Path 1","ix":1,"d":1,"ks":{"a":0,"k":{"c":true,"i":[[0,28.677],[0,0],[28.678,0],[0,0]],"o":[[0,0],[0,28.678],[0,0],[-28.668,-0.001]],"v":[[-95.188,-25.96],[95.188,-25.96],[43.267,25.961],[-43.268,25.961]]},"ix":2}},{"ty":"fl","bm":0,"hd":false,"mn":"ADBE Vector Graphic - Fill","nm":"Fill 1","c":{"a":0,"k":[0.9765,0.7059,0.302],"ix":4},"r":1,"o":{"a":0,"k":100,"ix":5}},{"ty":"tr","a":{"a":0,"k":[0,0],"ix":1},"s":{"a":0,"k":[100,100],"ix":3},"sk":{"a":0,"k":0,"ix":4},"p":{"a":0,"k":[411.76,342.532],"ix":2},"r":{"a":0,"k":0,"ix":6},"sa":{"a":0,"k":0,"ix":5},"o":{"a":0,"k":100,"ix":7}}]},{"ty":"gr","bm":0,"hd":false,"mn":"ADBE Vector Group","nm":"Group 3","ix":3,"cix":2,"np":4,"it":[{"ty":"sh","bm":0,"hd":false,"mn":"ADBE Vector Shape - Group","nm":"Path 1","ix":1,"d":1,"ks":{"a":0,"k":{"c":true,"i":[[1.998,4.344],[0,0],[0,0],[4.345,1.99],[-1.99,4.344],[0,0],[-4.344,-1.991],[-0.866,-1.886],[0,0],[4.345,-1.99]],"o":[[0,0],[0,0],[-1.99,4.344],[-4.344,-1.99],[0,0],[1.99,-4.344],[1.886,0.865],[0,0],[1.99,4.344],[-4.343,1.999]],"v":[[84.315,103.512],[0.601,-79.145],[-83.113,103.512],[-94.588,107.77],[-98.846,96.296],[-7.266,-103.521],[4.208,-107.778],[8.466,-103.521],[100.046,96.296],[95.788,107.77]]},"ix":2}},{"ty":"fl","bm":0,"hd":false,"mn":"ADBE Vector Graphic - Fill","nm":"Fill 1","c":{"a":0,"k":[0.9412,0.8941,0.8392],"ix":4},"r":1,"o":{"a":0,"k":100,"ix":5}},{"ty":"tr","a":{"a":0,"k":[0,0],"ix":1},"s":{"a":0,"k":[100,100],"ix":3},"sk":{"a":0,"k":0,"ix":4},"p":{"a":0,"k":[411.159,208.802],"ix":2},"r":{"a":0,"k":0,"ix":6},"sa":{"a":0,"k":0,"ix":5},"o":{"a":0,"k":100,"ix":7}}]}],"ind":2}]},{"nm":"","id":"comp_5","layers":[{"ty":4,"nm":"Layer 1 Outlines","sr":1,"st":0,"op":120,"ip":0,"hd":false,"ddd":0,"bm":0,"hasMask":false,"ao":0,"ks":{"a":{"a":0,"k":[257.5,257.5,0],"ix":1},"s":{"a":0,"k":[100,100,100],"ix":6},"sk":{"a":0,"k":0},"p":{"a":0,"k":[257.5,257.5,0],"ix":2},"r":{"a":0,"k":0,"ix":10},"sa":{"a":0,"k":0},"o":{"a":0,"k":100,"ix":11}},"ef":[],"shapes":[{"ty":"gr","bm":0,"hd":false,"mn":"ADBE Vector Group","nm":"Group 1","ix":1,"cix":2,"np":4,"it":[{"ty":"sh","bm":0,"hd":false,"mn":"ADBE Vector Shape - Group","nm":"Path 1","ix":1,"d":1,"ks":{"a":0,"k":{"c":true,"i":[[53.01,0],[0,53.011],[-53.01,0],[0,-53.01]],"o":[[-53.01,0],[0,-53.01],[53.01,0],[0,53.011]],"v":[[0,95.984],[-95.984,0],[0,-95.983],[95.984,0]]},"ix":2}},{"ty":"sh","bm":0,"hd":false,"mn":"ADBE Vector Shape - Group","nm":"Path 2","ix":2,"d":1,"ks":{"a":0,"k":{"c":true,"i":[[79.479,0.09],[0,-79.513],[-79.514,0],[0,79.518]],"o":[[-79.514,0],[0,79.518],[79.514,0],[-0.089,-79.478]],"v":[[0,-143.975],[-143.975,0],[0,143.976],[143.975,0]]},"ix":2}},{"ty":"mm","bm":0,"hd":false,"mn":"ADBE Vector Filter - Merge","nm":"Merge Paths 1","mm":1},{"ty":"fl","bm":0,"hd":false,"mn":"ADBE Vector Graphic - Fill","nm":"Fill 1","c":{"a":0,"k":[0.9843,0.651,0.1216],"ix":4},"r":1,"o":{"a":0,"k":100,"ix":5}},{"ty":"tr","a":{"a":0,"k":[0,0],"ix":1},"s":{"a":0,"k":[100,100],"ix":3},"sk":{"a":0,"k":0,"ix":4},"p":{"a":0,"k":[255.956,257.043],"ix":2},"r":{"a":0,"k":0,"ix":6},"sa":{"a":0,"k":0,"ix":5},"o":{"a":0,"k":100,"ix":7}}]},{"ty":"gr","bm":0,"hd":false,"mn":"ADBE Vector Group","nm":"Group 2","ix":2,"cix":2,"np":4,"it":[{"ty":"sh","bm":0,"hd":false,"mn":"ADBE Vector Shape - Group","nm":"Path 1","ix":1,"d":1,"ks":{"a":0,"k":{"c":true,"i":[[53.01,0],[0,53.011],[-53.01,0],[0,-53.01]],"o":[[-53.01,0],[0,-53.01],[53.01,0],[0,53.011]],"v":[[0,95.983],[-95.984,-0.001],[0,-95.984],[95.984,-0.001]]},"ix":2}},{"ty":"sh","bm":0,"hd":false,"mn":"ADBE Vector Shape - Group","nm":"Path 2","ix":2,"d":1,"ks":{"a":0,"k":{"c":true,"i":[[0,0],[0,0],[0,0],[0,0],[0,0],[0,0],[0,0],[0,0],[0,0],[0,0],[0,0],[0,0],[0,0],[0,0],[0,0],[0,0],[0,0],[0,0],[0,0],[0,0],[0,0],[0,0],[0,0],[0,0],[0,0],[0,0],[0,0],[0,0],[0,0],[0,0],[0,0],[0,0]],"o":[[0,0],[0,0],[0,0],[0,0],[0,0],[0,0],[0,0],[0,0],[0,0],[0,0],[0,0],[0,0],[0,0],[0,0],[0,0],[0,0],[0,0],[0,0],[0,0],[0,0],[0,0],[0,0],[0,0],[0,0],[0,0],[0,0],[0,0],[0,0],[0,0],[0,0],[0,0],[0,0]],"v":[[255.956,36.474],[255.956,-36.475],[193.967,-65.829],[183.695,-90.591],[206.781,-155.173],[155.173,-206.782],[90.543,-183.68],[65.829,-193.917],[36.474,-255.957],[-36.474,-255.957],[-65.844,-193.917],[-90.559,-183.68],[-155.173,-206.782],[-206.781,-155.173],[-183.695,-90.575],[-193.967,-65.814],[-255.956,-36.475],[-255.956,36.474],[-193.967,65.828],[-183.695,90.593],[-206.781,155.172],[-155.173,206.78],[-90.578,183.698],[-65.813,193.966],[-36.474,255.957],[36.474,255.957],[65.829,193.966],[90.594,183.698],[155.173,206.78],[206.781,155.172],[183.695,90.578],[193.967,65.812]]},"ix":2}},{"ty":"mm","bm":0,"hd":false,"mn":"ADBE Vector Filter - Merge","nm":"Merge Paths 1","mm":1},{"ty":"fl","bm":0,"hd":false,"mn":"ADBE Vector Graphic - Fill","nm":"Fill 1","c":{"a":0,"k":[1,0.7961,0.3529],"ix":4},"r":1,"o":{"a":0,"k":100,"ix":5}},{"ty":"tr","a":{"a":0,"k":[0,0],"ix":1},"s":{"a":0,"k":[100,100],"ix":3},"sk":{"a":0,"k":0,"ix":4},"p":{"a":0,"k":[255.956,257.043],"ix":2},"r":{"a":0,"k":0,"ix":6},"sa":{"a":0,"k":0,"ix":5},"o":{"a":0,"k":100,"ix":7}}]}],"ind":1}]}]}